{
  "Help Page - Pattern Scripts plugin for JMRI": "Help Page - Pattern Scripts plugin for JMRI", 
  "Introduction": "Introduction", 
  "Key": "Key", 
  "Organization": "Organization", 
  "Pattern Report for Track Window": "Pattern Report for Track Window", 
  "Pattern Scripts Subroutine": "Pattern Scripts Subroutine", 
  "Plugin Layout": "Plugin Layout", 
  "Track Pattern and Switch List JSON format": "Track Pattern and Switch List JSON format", 
  "Video Documentation": "Video Documentation", 
  "version": 20220101
}